{
    "total": [
        {
            "id": "61550080675171",
            "count": 0
        },
        {
            "id": "61550106620238",
            "count": 0
        },
        {
            "id": "61550331548866",
            "count": 0
        },
        {
            "id": "61550421464161",
            "count": 14
        },
        {
            "id": "61550625359235",
            "count": 0
        },
        {
            "id": "61550884707384",
            "count": 0
        },
        {
            "id": "61551064297194",
            "count": 0
        },
        {
            "id": "61551610380150",
            "count": 0
        },
        {
            "id": "61551728403713",
            "count": 0
        },
        {
            "id": "61552087054076",
            "count": 0
        },
        {
            "id": "61552363232319",
            "count": 0
        },
        {
            "id": "61552714392864",
            "count": 0
        },
        {
            "id": "61553732968524",
            "count": 0
        },
        {
            "id": "61554081564947",
            "count": 0
        },
        {
            "id": "61554086375168",
            "count": 0
        },
        {
            "id": "61554202714324",
            "count": 0
        },
        {
            "id": "61554509456360",
            "count": 0
        },
        {
            "id": "61554762550169",
            "count": 0
        },
        {
            "id": "61555192043976",
            "count": 0
        },
        {
            "id": "61555209361865",
            "count": 0
        },
        {
            "id": "61555676969658",
            "count": 0
        },
        {
            "id": "61555699418920",
            "count": 23
        },
        {
            "id": "61555745235474",
            "count": 0
        },
        {
            "id": "61555784052126",
            "count": 0
        },
        {
            "id": "61555811091285",
            "count": 0
        },
        {
            "id": "61555829786705",
            "count": 0
        },
        {
            "id": "61555852627229",
            "count": 0
        },
        {
            "id": "61555910235673",
            "count": 0
        },
        {
            "id": "61556303199429",
            "count": 0
        },
        {
            "id": "61556313458896",
            "count": 0
        },
        {
            "id": "61556314261440",
            "count": 0
        },
        {
            "id": "61556385214163",
            "count": 0
        },
        {
            "id": "61556484100924",
            "count": 8
        },
        {
            "id": "61557006013585",
            "count": 0
        },
        {
            "id": "61557026555593",
            "count": 0
        },
        {
            "id": "61557047054611",
            "count": 0
        },
        {
            "id": "61557048011494",
            "count": 3
        },
        {
            "id": "61557077737120",
            "count": 0
        },
        {
            "id": "61557144780643",
            "count": 0
        },
        {
            "id": "61557168401537",
            "count": 0
        },
        {
            "id": "61557177372835",
            "count": 0
        },
        {
            "id": "61557289900234",
            "count": 0
        },
        {
            "id": "61557319186288",
            "count": 0
        },
        {
            "id": "61557390626189",
            "count": 0
        },
        {
            "id": "61557411175737",
            "count": 0
        },
        {
            "id": "61557429725255",
            "count": 0
        },
        {
            "id": "61557432521428",
            "count": 0
        },
        {
            "id": "61557456223679",
            "count": 0
        },
        {
            "id": "61557471395532",
            "count": 0
        },
        {
            "id": "61557581025858",
            "count": 0
        },
        {
            "id": "61557592673166",
            "count": 0
        },
        {
            "id": "61557598033754",
            "count": 0
        },
        {
            "id": "61557618910797",
            "count": 0
        },
        {
            "id": "61557689740885",
            "count": 0
        },
        {
            "id": "61557696974408",
            "count": 0
        },
        {
            "id": "61557704375944",
            "count": 0
        },
        {
            "id": "61557769444501",
            "count": 2
        },
        {
            "id": "61557775345235",
            "count": 0
        },
        {
            "id": "61557791273517",
            "count": 0
        },
        {
            "id": "61557896137572",
            "count": 0
        },
        {
            "id": "61557896346261",
            "count": 0
        },
        {
            "id": "61557917590500",
            "count": 0
        },
        {
            "id": "61557947014943",
            "count": 0
        },
        {
            "id": "61557952567953",
            "count": 0
        },
        {
            "id": "61557954244202",
            "count": 0
        },
        {
            "id": "61557957270776",
            "count": 0
        },
        {
            "id": "61557982981751",
            "count": 0
        },
        {
            "id": "61558056820646",
            "count": 0
        },
        {
            "id": "61558066311422",
            "count": 0
        },
        {
            "id": "61558066717202",
            "count": 0
        },
        {
            "id": "61558091532324",
            "count": 7
        },
        {
            "id": "61558102985986",
            "count": 0
        },
        {
            "id": "61558117460920",
            "count": 0
        },
        {
            "id": "61558147571973",
            "count": 0
        },
        {
            "id": "61558151550260",
            "count": 0
        },
        {
            "id": "61558153930372",
            "count": 0
        },
        {
            "id": "61558180829456",
            "count": 0
        },
        {
            "id": "61558181695151",
            "count": 0
        },
        {
            "id": "61558205753773",
            "count": 0
        },
        {
            "id": "61558237297023",
            "count": 0
        },
        {
            "id": "61558258490169",
            "count": 0
        },
        {
            "id": "61558268523893",
            "count": 0
        },
        {
            "id": "61558347184038",
            "count": 0
        },
        {
            "id": "61558390083051",
            "count": 0
        },
        {
            "id": "61558397637180",
            "count": 0
        },
        {
            "id": "61558435830663",
            "count": 0
        },
        {
            "id": "61558447191630",
            "count": 0
        },
        {
            "id": "61558449145287",
            "count": 1
        },
        {
            "id": "61558524955758",
            "count": 0
        },
        {
            "id": "61558544691317",
            "count": 0
        },
        {
            "id": "61558563922639",
            "count": 0
        },
        {
            "id": "61558596205042",
            "count": 0
        },
        {
            "id": "61558612671199",
            "count": 0
        },
        {
            "id": "61558643512558",
            "count": 0
        },
        {
            "id": "100032105479807",
            "count": 0
        },
        {
            "id": "100040024218992",
            "count": 0
        },
        {
            "id": "100047113003772",
            "count": 0
        },
        {
            "id": "100049199887992",
            "count": 0
        },
        {
            "id": "100050221821104",
            "count": 0
        },
        {
            "id": "100055872052608",
            "count": 0
        },
        {
            "id": "100055951692141",
            "count": 0
        },
        {
            "id": "100060800204947",
            "count": 0
        },
        {
            "id": "100064232722079",
            "count": 0
        },
        {
            "id": "100066299686713",
            "count": 0
        },
        {
            "id": "100068358914827",
            "count": 0
        },
        {
            "id": "100069865651868",
            "count": 0
        },
        {
            "id": "100070387955907",
            "count": 0
        },
        {
            "id": "100073034272263",
            "count": 0
        },
        {
            "id": "100073733472928",
            "count": 0
        },
        {
            "id": "100073803650987",
            "count": 0
        },
        {
            "id": "100075267708089",
            "count": 0
        },
        {
            "id": "100075296892322",
            "count": 0
        },
        {
            "id": "100076682246407",
            "count": 0
        },
        {
            "id": "100076723602756",
            "count": 0
        },
        {
            "id": "100077907068618",
            "count": 0
        },
        {
            "id": "100078581122003",
            "count": 0
        },
        {
            "id": "100080813970369",
            "count": 0
        },
        {
            "id": "100082252157847",
            "count": 0
        },
        {
            "id": "100083168404966",
            "count": 0
        },
        {
            "id": "100083222255334",
            "count": 0
        },
        {
            "id": "100083836715812",
            "count": 0
        },
        {
            "id": "100084709971104",
            "count": 0
        },
        {
            "id": "100084747420987",
            "count": 0
        },
        {
            "id": "100086652897472",
            "count": 0
        },
        {
            "id": "100087249558562",
            "count": 0
        },
        {
            "id": "100087393938794",
            "count": 0
        },
        {
            "id": "100087910604713",
            "count": 3
        },
        {
            "id": "100089105300786",
            "count": 0
        },
        {
            "id": "100090839765752",
            "count": 0
        },
        {
            "id": "100091002905367",
            "count": 2
        },
        {
            "id": "100091869600825",
            "count": 0
        },
        {
            "id": "100092405541106",
            "count": 0
        },
        {
            "id": "100092413470382",
            "count": 0
        },
        {
            "id": "100092413526985",
            "count": 0
        },
        {
            "id": "100092710913924",
            "count": 0
        },
        {
            "id": "100093011534845",
            "count": 0
        },
        {
            "id": "100093193606210",
            "count": 0
        },
        {
            "id": "100094271921141",
            "count": 0
        },
        {
            "id": "100094358447078",
            "count": 0
        },
        {
            "id": "100094721081515",
            "count": 0
        },
        {
            "id": "100095388105984",
            "count": 0
        },
        {
            "id": "100095490970455",
            "count": 0
        }
    ],
    "week": [
        {
            "id": "61550080675171",
            "count": 0
        },
        {
            "id": "61550106620238",
            "count": 0
        },
        {
            "id": "61550331548866",
            "count": 0
        },
        {
            "id": "61550421464161",
            "count": 14
        },
        {
            "id": "61550625359235",
            "count": 0
        },
        {
            "id": "61550884707384",
            "count": 0
        },
        {
            "id": "61551064297194",
            "count": 0
        },
        {
            "id": "61551610380150",
            "count": 0
        },
        {
            "id": "61551728403713",
            "count": 0
        },
        {
            "id": "61552087054076",
            "count": 0
        },
        {
            "id": "61552363232319",
            "count": 0
        },
        {
            "id": "61552714392864",
            "count": 0
        },
        {
            "id": "61553732968524",
            "count": 0
        },
        {
            "id": "61554081564947",
            "count": 0
        },
        {
            "id": "61554086375168",
            "count": 0
        },
        {
            "id": "61554202714324",
            "count": 0
        },
        {
            "id": "61554509456360",
            "count": 0
        },
        {
            "id": "61554762550169",
            "count": 0
        },
        {
            "id": "61555192043976",
            "count": 0
        },
        {
            "id": "61555209361865",
            "count": 0
        },
        {
            "id": "61555676969658",
            "count": 0
        },
        {
            "id": "61555699418920",
            "count": 23
        },
        {
            "id": "61555745235474",
            "count": 0
        },
        {
            "id": "61555784052126",
            "count": 0
        },
        {
            "id": "61555811091285",
            "count": 0
        },
        {
            "id": "61555829786705",
            "count": 0
        },
        {
            "id": "61555852627229",
            "count": 0
        },
        {
            "id": "61555910235673",
            "count": 0
        },
        {
            "id": "61556303199429",
            "count": 0
        },
        {
            "id": "61556313458896",
            "count": 0
        },
        {
            "id": "61556314261440",
            "count": 0
        },
        {
            "id": "61556385214163",
            "count": 0
        },
        {
            "id": "61556484100924",
            "count": 8
        },
        {
            "id": "61557006013585",
            "count": 0
        },
        {
            "id": "61557026555593",
            "count": 0
        },
        {
            "id": "61557047054611",
            "count": 0
        },
        {
            "id": "61557048011494",
            "count": 3
        },
        {
            "id": "61557077737120",
            "count": 0
        },
        {
            "id": "61557144780643",
            "count": 0
        },
        {
            "id": "61557168401537",
            "count": 0
        },
        {
            "id": "61557177372835",
            "count": 0
        },
        {
            "id": "61557289900234",
            "count": 0
        },
        {
            "id": "61557319186288",
            "count": 0
        },
        {
            "id": "61557390626189",
            "count": 0
        },
        {
            "id": "61557411175737",
            "count": 0
        },
        {
            "id": "61557429725255",
            "count": 0
        },
        {
            "id": "61557432521428",
            "count": 0
        },
        {
            "id": "61557456223679",
            "count": 0
        },
        {
            "id": "61557471395532",
            "count": 0
        },
        {
            "id": "61557581025858",
            "count": 0
        },
        {
            "id": "61557592673166",
            "count": 0
        },
        {
            "id": "61557598033754",
            "count": 0
        },
        {
            "id": "61557618910797",
            "count": 0
        },
        {
            "id": "61557689740885",
            "count": 0
        },
        {
            "id": "61557696974408",
            "count": 0
        },
        {
            "id": "61557704375944",
            "count": 0
        },
        {
            "id": "61557769444501",
            "count": 2
        },
        {
            "id": "61557775345235",
            "count": 0
        },
        {
            "id": "61557791273517",
            "count": 0
        },
        {
            "id": "61557896137572",
            "count": 0
        },
        {
            "id": "61557896346261",
            "count": 0
        },
        {
            "id": "61557917590500",
            "count": 0
        },
        {
            "id": "61557947014943",
            "count": 0
        },
        {
            "id": "61557952567953",
            "count": 0
        },
        {
            "id": "61557954244202",
            "count": 0
        },
        {
            "id": "61557957270776",
            "count": 0
        },
        {
            "id": "61557982981751",
            "count": 0
        },
        {
            "id": "61558056820646",
            "count": 0
        },
        {
            "id": "61558066311422",
            "count": 0
        },
        {
            "id": "61558066717202",
            "count": 0
        },
        {
            "id": "61558091532324",
            "count": 7
        },
        {
            "id": "61558102985986",
            "count": 0
        },
        {
            "id": "61558117460920",
            "count": 0
        },
        {
            "id": "61558147571973",
            "count": 0
        },
        {
            "id": "61558151550260",
            "count": 0
        },
        {
            "id": "61558153930372",
            "count": 0
        },
        {
            "id": "61558180829456",
            "count": 0
        },
        {
            "id": "61558181695151",
            "count": 0
        },
        {
            "id": "61558205753773",
            "count": 0
        },
        {
            "id": "61558237297023",
            "count": 0
        },
        {
            "id": "61558258490169",
            "count": 0
        },
        {
            "id": "61558268523893",
            "count": 0
        },
        {
            "id": "61558347184038",
            "count": 0
        },
        {
            "id": "61558390083051",
            "count": 0
        },
        {
            "id": "61558397637180",
            "count": 0
        },
        {
            "id": "61558435830663",
            "count": 0
        },
        {
            "id": "61558447191630",
            "count": 0
        },
        {
            "id": "61558449145287",
            "count": 1
        },
        {
            "id": "61558524955758",
            "count": 0
        },
        {
            "id": "61558544691317",
            "count": 0
        },
        {
            "id": "61558563922639",
            "count": 0
        },
        {
            "id": "61558596205042",
            "count": 0
        },
        {
            "id": "61558612671199",
            "count": 0
        },
        {
            "id": "61558643512558",
            "count": 0
        },
        {
            "id": "100032105479807",
            "count": 0
        },
        {
            "id": "100040024218992",
            "count": 0
        },
        {
            "id": "100047113003772",
            "count": 0
        },
        {
            "id": "100049199887992",
            "count": 0
        },
        {
            "id": "100050221821104",
            "count": 0
        },
        {
            "id": "100055872052608",
            "count": 0
        },
        {
            "id": "100055951692141",
            "count": 0
        },
        {
            "id": "100060800204947",
            "count": 0
        },
        {
            "id": "100064232722079",
            "count": 0
        },
        {
            "id": "100066299686713",
            "count": 0
        },
        {
            "id": "100068358914827",
            "count": 0
        },
        {
            "id": "100069865651868",
            "count": 0
        },
        {
            "id": "100070387955907",
            "count": 0
        },
        {
            "id": "100073034272263",
            "count": 0
        },
        {
            "id": "100073733472928",
            "count": 0
        },
        {
            "id": "100073803650987",
            "count": 0
        },
        {
            "id": "100075267708089",
            "count": 0
        },
        {
            "id": "100075296892322",
            "count": 0
        },
        {
            "id": "100076682246407",
            "count": 0
        },
        {
            "id": "100076723602756",
            "count": 0
        },
        {
            "id": "100077907068618",
            "count": 0
        },
        {
            "id": "100078581122003",
            "count": 0
        },
        {
            "id": "100080813970369",
            "count": 0
        },
        {
            "id": "100082252157847",
            "count": 0
        },
        {
            "id": "100083168404966",
            "count": 0
        },
        {
            "id": "100083222255334",
            "count": 0
        },
        {
            "id": "100083836715812",
            "count": 0
        },
        {
            "id": "100084709971104",
            "count": 0
        },
        {
            "id": "100084747420987",
            "count": 0
        },
        {
            "id": "100086652897472",
            "count": 0
        },
        {
            "id": "100087249558562",
            "count": 0
        },
        {
            "id": "100087393938794",
            "count": 0
        },
        {
            "id": "100087910604713",
            "count": 3
        },
        {
            "id": "100089105300786",
            "count": 0
        },
        {
            "id": "100090839765752",
            "count": 0
        },
        {
            "id": "100091002905367",
            "count": 2
        },
        {
            "id": "100091869600825",
            "count": 0
        },
        {
            "id": "100092405541106",
            "count": 0
        },
        {
            "id": "100092413470382",
            "count": 0
        },
        {
            "id": "100092413526985",
            "count": 0
        },
        {
            "id": "100092710913924",
            "count": 0
        },
        {
            "id": "100093011534845",
            "count": 0
        },
        {
            "id": "100093193606210",
            "count": 0
        },
        {
            "id": "100094271921141",
            "count": 0
        },
        {
            "id": "100094358447078",
            "count": 0
        },
        {
            "id": "100094721081515",
            "count": 0
        },
        {
            "id": "100095388105984",
            "count": 0
        },
        {
            "id": "100095490970455",
            "count": 0
        }
    ],
    "day": [
        {
            "id": "61550080675171",
            "count": 0
        },
        {
            "id": "61550106620238",
            "count": 0
        },
        {
            "id": "61550331548866",
            "count": 0
        },
        {
            "id": "61550421464161",
            "count": 14
        },
        {
            "id": "61550625359235",
            "count": 0
        },
        {
            "id": "61550884707384",
            "count": 0
        },
        {
            "id": "61551064297194",
            "count": 0
        },
        {
            "id": "61551610380150",
            "count": 0
        },
        {
            "id": "61551728403713",
            "count": 0
        },
        {
            "id": "61552087054076",
            "count": 0
        },
        {
            "id": "61552363232319",
            "count": 0
        },
        {
            "id": "61552714392864",
            "count": 0
        },
        {
            "id": "61553732968524",
            "count": 0
        },
        {
            "id": "61554081564947",
            "count": 0
        },
        {
            "id": "61554086375168",
            "count": 0
        },
        {
            "id": "61554202714324",
            "count": 0
        },
        {
            "id": "61554509456360",
            "count": 0
        },
        {
            "id": "61554762550169",
            "count": 0
        },
        {
            "id": "61555192043976",
            "count": 0
        },
        {
            "id": "61555209361865",
            "count": 0
        },
        {
            "id": "61555676969658",
            "count": 0
        },
        {
            "id": "61555699418920",
            "count": 23
        },
        {
            "id": "61555745235474",
            "count": 0
        },
        {
            "id": "61555784052126",
            "count": 0
        },
        {
            "id": "61555811091285",
            "count": 0
        },
        {
            "id": "61555829786705",
            "count": 0
        },
        {
            "id": "61555852627229",
            "count": 0
        },
        {
            "id": "61555910235673",
            "count": 0
        },
        {
            "id": "61556303199429",
            "count": 0
        },
        {
            "id": "61556313458896",
            "count": 0
        },
        {
            "id": "61556314261440",
            "count": 0
        },
        {
            "id": "61556385214163",
            "count": 0
        },
        {
            "id": "61556484100924",
            "count": 8
        },
        {
            "id": "61557006013585",
            "count": 0
        },
        {
            "id": "61557026555593",
            "count": 0
        },
        {
            "id": "61557047054611",
            "count": 0
        },
        {
            "id": "61557048011494",
            "count": 3
        },
        {
            "id": "61557077737120",
            "count": 0
        },
        {
            "id": "61557144780643",
            "count": 0
        },
        {
            "id": "61557168401537",
            "count": 0
        },
        {
            "id": "61557177372835",
            "count": 0
        },
        {
            "id": "61557289900234",
            "count": 0
        },
        {
            "id": "61557319186288",
            "count": 0
        },
        {
            "id": "61557390626189",
            "count": 0
        },
        {
            "id": "61557411175737",
            "count": 0
        },
        {
            "id": "61557429725255",
            "count": 0
        },
        {
            "id": "61557432521428",
            "count": 0
        },
        {
            "id": "61557456223679",
            "count": 0
        },
        {
            "id": "61557471395532",
            "count": 0
        },
        {
            "id": "61557581025858",
            "count": 0
        },
        {
            "id": "61557592673166",
            "count": 0
        },
        {
            "id": "61557598033754",
            "count": 0
        },
        {
            "id": "61557618910797",
            "count": 0
        },
        {
            "id": "61557689740885",
            "count": 0
        },
        {
            "id": "61557696974408",
            "count": 0
        },
        {
            "id": "61557704375944",
            "count": 0
        },
        {
            "id": "61557769444501",
            "count": 2
        },
        {
            "id": "61557775345235",
            "count": 0
        },
        {
            "id": "61557791273517",
            "count": 0
        },
        {
            "id": "61557896137572",
            "count": 0
        },
        {
            "id": "61557896346261",
            "count": 0
        },
        {
            "id": "61557917590500",
            "count": 0
        },
        {
            "id": "61557947014943",
            "count": 0
        },
        {
            "id": "61557952567953",
            "count": 0
        },
        {
            "id": "61557954244202",
            "count": 0
        },
        {
            "id": "61557957270776",
            "count": 0
        },
        {
            "id": "61557982981751",
            "count": 0
        },
        {
            "id": "61558056820646",
            "count": 0
        },
        {
            "id": "61558066311422",
            "count": 0
        },
        {
            "id": "61558066717202",
            "count": 0
        },
        {
            "id": "61558091532324",
            "count": 7
        },
        {
            "id": "61558102985986",
            "count": 0
        },
        {
            "id": "61558117460920",
            "count": 0
        },
        {
            "id": "61558147571973",
            "count": 0
        },
        {
            "id": "61558151550260",
            "count": 0
        },
        {
            "id": "61558153930372",
            "count": 0
        },
        {
            "id": "61558180829456",
            "count": 0
        },
        {
            "id": "61558181695151",
            "count": 0
        },
        {
            "id": "61558205753773",
            "count": 0
        },
        {
            "id": "61558237297023",
            "count": 0
        },
        {
            "id": "61558258490169",
            "count": 0
        },
        {
            "id": "61558268523893",
            "count": 0
        },
        {
            "id": "61558347184038",
            "count": 0
        },
        {
            "id": "61558390083051",
            "count": 0
        },
        {
            "id": "61558397637180",
            "count": 0
        },
        {
            "id": "61558435830663",
            "count": 0
        },
        {
            "id": "61558447191630",
            "count": 0
        },
        {
            "id": "61558449145287",
            "count": 1
        },
        {
            "id": "61558524955758",
            "count": 0
        },
        {
            "id": "61558544691317",
            "count": 0
        },
        {
            "id": "61558563922639",
            "count": 0
        },
        {
            "id": "61558596205042",
            "count": 0
        },
        {
            "id": "61558612671199",
            "count": 0
        },
        {
            "id": "61558643512558",
            "count": 0
        },
        {
            "id": "100032105479807",
            "count": 0
        },
        {
            "id": "100040024218992",
            "count": 0
        },
        {
            "id": "100047113003772",
            "count": 0
        },
        {
            "id": "100049199887992",
            "count": 0
        },
        {
            "id": "100050221821104",
            "count": 0
        },
        {
            "id": "100055872052608",
            "count": 0
        },
        {
            "id": "100055951692141",
            "count": 0
        },
        {
            "id": "100060800204947",
            "count": 0
        },
        {
            "id": "100064232722079",
            "count": 0
        },
        {
            "id": "100066299686713",
            "count": 0
        },
        {
            "id": "100068358914827",
            "count": 0
        },
        {
            "id": "100069865651868",
            "count": 0
        },
        {
            "id": "100070387955907",
            "count": 0
        },
        {
            "id": "100073034272263",
            "count": 0
        },
        {
            "id": "100073733472928",
            "count": 0
        },
        {
            "id": "100073803650987",
            "count": 0
        },
        {
            "id": "100075267708089",
            "count": 0
        },
        {
            "id": "100075296892322",
            "count": 0
        },
        {
            "id": "100076682246407",
            "count": 0
        },
        {
            "id": "100076723602756",
            "count": 0
        },
        {
            "id": "100077907068618",
            "count": 0
        },
        {
            "id": "100078581122003",
            "count": 0
        },
        {
            "id": "100080813970369",
            "count": 0
        },
        {
            "id": "100082252157847",
            "count": 0
        },
        {
            "id": "100083168404966",
            "count": 0
        },
        {
            "id": "100083222255334",
            "count": 0
        },
        {
            "id": "100083836715812",
            "count": 0
        },
        {
            "id": "100084709971104",
            "count": 0
        },
        {
            "id": "100084747420987",
            "count": 0
        },
        {
            "id": "100086652897472",
            "count": 0
        },
        {
            "id": "100087249558562",
            "count": 0
        },
        {
            "id": "100087393938794",
            "count": 0
        },
        {
            "id": "100087910604713",
            "count": 3
        },
        {
            "id": "100089105300786",
            "count": 0
        },
        {
            "id": "100090839765752",
            "count": 0
        },
        {
            "id": "100091002905367",
            "count": 2
        },
        {
            "id": "100091869600825",
            "count": 0
        },
        {
            "id": "100092405541106",
            "count": 0
        },
        {
            "id": "100092413470382",
            "count": 0
        },
        {
            "id": "100092413526985",
            "count": 0
        },
        {
            "id": "100092710913924",
            "count": 0
        },
        {
            "id": "100093011534845",
            "count": 0
        },
        {
            "id": "100093193606210",
            "count": 0
        },
        {
            "id": "100094271921141",
            "count": 0
        },
        {
            "id": "100094358447078",
            "count": 0
        },
        {
            "id": "100094721081515",
            "count": 0
        },
        {
            "id": "100095388105984",
            "count": 0
        },
        {
            "id": "100095490970455",
            "count": 0
        }
    ],
    "time": 1
}